[{"centered":"AP","radius":3.0,"state":"Andhra Pradesh","info":[7,9.86,0,0.0,0,0.0,0,0.0]},{"centered":"BR","radius":1.0,"state":"Bihar","info":[2,2.82,0,0.0,0,0.0,1,50.0]},{"centered":"CT","radius":1.0,"state":"Chhattisgarh","info":[1,1.41,0,0.0,0,0.0,0,0.0]},{"centered":"DL","radius":12.0,"state":"Delhi","info":[28,39.44,1,7.14,5,45.45,1,50.0]},{"centered":"GJ","radius":13.0,"state":"Gujarat","info":[29,40.85,0,0.0,0,0.0,1,50.0]},{"centered":"HR","radius":6.0,"state":"Haryana","info":[12,16.9,14,100.0,11,100.0,0,0.0]},{"centered":"HP","radius":2.0,"state":"Himachal Pradesh","info":[3,4.23,0,0.0,0,0.0,1,50.0]},{"centered":"KA","radius":14.0,"state":"Karnataka","info":[33,46.48,0,0.0,2,18.18,1,50.0]},{"centered":"KL","radius":26.0,"state":"Kerala","info":[60,84.51,7,50.0,3,27.27,0,0.0]},{"centered":"MP","radius":3.0,"state":"Madhya Pradesh","info":[6,8.45,0,0.0,0,0.0,0,0.0]},{"centered":"MH","radius":31.0,"state":"Maharashtra","info":[71,100.0,3,21.43,0,0.0,2,100.0]},{"centered":"OD","radius":1.0,"state":"Odisha","info":[2,2.82,0,0.0,0,0.0,0,0.0]},{"centered":"PY","radius":1.0,"state":"Puducherry","info":[1,1.41,0,0.0,0,0.0,0,0.0]},{"centered":"PB","radius":9.0,"state":"Punjab","info":[21,29.58,0,0.0,0,0.0,1,50.0]},{"centered":"RJ","radius":11.0,"state":"Rajasthan","info":[26,36.62,2,14.29,3,27.27,0,0.0]},{"centered":"TN","radius":3.0,"state":"Tamil Nadu","info":[7,9.86,2,14.29,1,9.09,0,0.0]},{"centered":"TS","radius":10.0,"state":"Telengana","info":[22,30.99,10,71.43,1,9.09,0,0.0]},{"centered":"CH","radius":3.0,"state":"Chandigarh","info":[6,8.45,0,0.0,0,0.0,0,0.0]},{"centered":"JK","radius":2.0,"state":"Jammu and Kashmir","info":[4,5.63,0,0.0,0,0.0,0,0.0]},{"centered":"LK","radius":6.0,"state":"Ladakh","info":[13,18.31,0,0.0,0,0.0,0,0.0]},{"centered":"UP","radius":13.0,"state":"Uttar Pradesh","info":[30,42.25,1,7.14,9,81.82,0,0.0]},{"centered":"UK","radius":2.0,"state":"Uttarakhand","info":[3,4.23,0,0.0,0,0.0,0,0.0]},{"centered":"WB","radius":3.0,"state":"West Bengal","info":[7,9.86,0,0.0,0,0.0,1,50.0]}]
